LICENSE
MANIFEST.in
README.md
requirements-test.txt
setup.py
logmein_app/__init__.py
logmein_app/security.py
logmein_app/tests.py
logmein_app/urls.py
logmein_app/views.py
logmein_app.egg-info/PKG-INFO
logmein_app.egg-info/SOURCES.txt
logmein_app.egg-info/dependency_links.txt
logmein_app.egg-info/entry_points.txt
logmein_app.egg-info/top_level.txt