Metadata-Version: 1.1
Name: logmein-app
Version: 0.0.3dev
Summary: Connect remotely to a django project
Home-page: https://github.com/raphapassini/logmein
Author: Raphael Passini Diniz
Author-email: UNKNOWN
License: MIT
Platform: any
Classifier: Intended Audience :: Developers
Classifier: License :: Freely Distributable
Classifier: Operating System :: OS Independent
Classifier: Programming Language :: Python
Classifier: Programming Language :: Python :: 2.6
Classifier: Programming Language :: Python :: 2.7
